api/__init__.py
apiessence/__init__.py
essenceApi-4.2.dist-info/METADATA
essenceApi-4.2.dist-info/WHEEL
essenceApi-4.2.dist-info/top_level.txt
essenceApi-4.2.dist-info/RECORD
